docs/clear_all_notebooks.py
docs/conf.py
docs/generate_logo.py
docs/run_all_notebooks.py
docs/utilities/cache_example.py
nlmod/__init__.py
nlmod/cache.py
nlmod/config.py
nlmod/epsg28992.py
nlmod/gis.py
nlmod/observations.py
nlmod/util.py
nlmod/version.py
nlmod/bin/mp7_2_002_provisional
nlmod/data/ahn/ellipsis_tiles.geojson
nlmod/data/bgt/bronhouder_names.json
nlmod/data/geotop/Lithoklasse.voleg
nlmod/data/geotop/Lithostratigrafie.voleg
nlmod/data/geotop/REF_GTP_LITHO_CLASS.csv
nlmod/data/geotop/REF_GTP_LITHO_CLASS.xlsx
nlmod/data/geotop/REF_GTP_STR_UNIT.csv
nlmod/data/geotop/REF_GTP_STR_UNIT.xlsx
nlmod/data/geotop/geo_eenheden.csv
nlmod/data/geotop/geotop.gleg
nlmod/data/geotop/hydraulische_parameterisering_geotop_noord-brabant_en_noord-_en_midden-limburg.csv
nlmod/data/geotop/litho_eenheden.csv
nlmod/data/regis/Tabellen.bij.naamgevingsreleases.REGIS.II.csv
nlmod/data/regis/regis_2_2.gleg
nlmod/data/shapes/opp_water.cpg
nlmod/data/shapes/opp_water.dbf
nlmod/data/shapes/opp_water.prj
nlmod/data/shapes/opp_water.qpj
nlmod/data/shapes/opp_water.shp
nlmod/data/shapes/opp_water.shx
nlmod/dims/__init__.py
nlmod/dims/attributes_encodings.py
nlmod/dims/base.py
nlmod/dims/grid.py
nlmod/dims/layers.py
nlmod/dims/rdp.py
nlmod/dims/resample.py
nlmod/dims/shared.py
nlmod/dims/time.py
nlmod/gwf/__init__.py
nlmod/gwf/gwf.py
nlmod/gwf/hfb.py
nlmod/gwf/lake.py
nlmod/gwf/output.py
nlmod/gwf/recharge.py
nlmod/gwf/surface_water.py
nlmod/gwf/wells.py
nlmod/gwt/__init__.py
nlmod/gwt/gwt.py
nlmod/gwt/output.py
nlmod/gwt/prepare.py
nlmod/mfoutput/__init__.py
nlmod/mfoutput/binaryfile.py
nlmod/mfoutput/mfoutput.py
nlmod/modpath/__init__.py
nlmod/modpath/modpath.py
nlmod/plot/__init__.py
nlmod/plot/dcs.py
nlmod/plot/flopy.py
nlmod/plot/plot.py
nlmod/plot/plotutil.py
nlmod/prt/__init__.py
nlmod/prt/prt.py
nlmod/read/__init__.py
nlmod/read/administrative.py
nlmod/read/ahn.py
nlmod/read/bgt.py
nlmod/read/bofek.py
nlmod/read/bro.py
nlmod/read/brp.py
nlmod/read/brt.py
nlmod/read/geotop.py
nlmod-0.11.1.dist-info/licenses/LICENSE
nlmod-0.11.1.dist-info/METADATA
nlmod-0.11.1.dist-info/WHEEL
nlmod-0.11.1.dist-info/top_level.txt
nlmod-0.11.1.dist-info/RECORD
