Metadata-Version: 2.4
Name: nlmod
Version: 0.11.1
Summary: Python package to build, run and visualize MODFLOW 6 groundwater models in the Netherlands.
Author: O.N. Ebbens, R.J. Caljé, D.A. Brakenhoff
Maintainer-email: "O.N. Ebbens" <o.ebbens@artesia-water.nl>, "R.J. Calje" <r.calje@artesia-water.nl>, "D.A. Brakenhoff" <d.brakenhoff@artesia-water.nl>
License: The MIT License (MIT)
Project-URL: homepage, https://github.com/gwmod/nlmod
Project-URL: repository, https://github.com/gwmod/nlmod
Project-URL: documentation, https://nlmod.readthedocs.io/en/latest/
Project-URL: installation, https://pypi.org/project/nlmod/
Keywords: hydrology,groundwater,modeling,MODFLOW,flopy
Classifier: Development Status :: 4 - Beta
Classifier: Intended Audience :: Science/Research
Classifier: Intended Audience :: Other Audience
Classifier: License :: OSI Approved :: MIT License
Classifier: Programming Language :: Python :: 3 :: Only
Classifier: Programming Language :: Python :: 3.10
Classifier: Programming Language :: Python :: 3.11
Classifier: Programming Language :: Python :: 3.12
Classifier: Programming Language :: Python :: 3.13
Classifier: Topic :: Scientific/Engineering :: Hydrology
Requires-Python: >=3.10
License-File: LICENSE
Requires-Dist: flopy>=3.3.6
Requires-Dist: xarray>=0.16.1
Requires-Dist: netcdf4>=1.7.2
Requires-Dist: rasterio>=1.1.0
Requires-Dist: rioxarray
Requires-Dist: affine>=0.3.1
Requires-Dist: geopandas
Requires-Dist: shapely>=2.0.0
Requires-Dist: matplotlib
Requires-Dist: dask
Requires-Dist: requests
Requires-Dist: scipy
Requires-Dist: bottleneck
Provides-Extra: full
Requires-Dist: nlmod[knmi]; extra == "full"
Requires-Dist: geocube; extra == "full"
Requires-Dist: rasterstats; extra == "full"
Requires-Dist: contextily; extra == "full"
Requires-Dist: scikit-image; extra == "full"
Requires-Dist: py7zr; extra == "full"
Requires-Dist: joblib; extra == "full"
Requires-Dist: colorama; extra == "full"
Requires-Dist: tqdm; extra == "full"
Requires-Dist: hydropandas>=0.9.2; extra == "full"
Requires-Dist: owslib>=0.24.1; extra == "full"
Requires-Dist: pyshp>=2.1.3; extra == "full"
Provides-Extra: knmi
Requires-Dist: h5netcdf; extra == "knmi"
Requires-Dist: h5py; extra == "knmi"
Requires-Dist: nlmod[grib]; extra == "knmi"
Provides-Extra: grib
Requires-Dist: cfgrib; extra == "grib"
Requires-Dist: ecmwflibs; extra == "grib"
Provides-Extra: test
Requires-Dist: pytest>=7; extra == "test"
Requires-Dist: pytest-cov; extra == "test"
Requires-Dist: pytest-dependency; extra == "test"
Provides-Extra: nbtest
Requires-Dist: nbformat; extra == "nbtest"
Requires-Dist: nbconvert>6.4.5; extra == "nbtest"
Provides-Extra: lint
Requires-Dist: ruff; extra == "lint"
Provides-Extra: ci
Requires-Dist: nlmod[full,lint,nbtest,test]; extra == "ci"
Provides-Extra: rtd
Requires-Dist: nlmod[full]; extra == "rtd"
Requires-Dist: ipython; extra == "rtd"
Requires-Dist: ipykernel; extra == "rtd"
Requires-Dist: ipywidgets; extra == "rtd"
Requires-Dist: myst-nb; extra == "rtd"
Requires-Dist: sphinx_rtd_theme; extra == "rtd"
Requires-Dist: nbconvert; extra == "rtd"
Requires-Dist: openpyxl; extra == "rtd"
Dynamic: license-file
